hcli_chat/__init__.py
hcli_chat/main.py
hcli_chat/commands/__init__.py
hcli_chat/commands/chat.py
hcli_chat/mcp/__init__.py
hcli_chat/mcp/mcp-plugin.py
hcli_chat/mcp/server.py
ida_hcli_chat-0.0.3.dist-info/METADATA
ida_hcli_chat-0.0.3.dist-info/WHEEL
ida_hcli_chat-0.0.3.dist-info/entry_points.txt
ida_hcli_chat-0.0.3.dist-info/top_level.txt
ida_hcli_chat-0.0.3.dist-info/RECORD
